setsig/__init__.py
setsig/core/__init__.py
setsig/tests/__init__.py
setsig/tests/test_1984.py
setsig-1.0.0.dist-info/licenses/LICENSE.txt
setsig-1.0.0.dist-info/METADATA
setsig-1.0.0.dist-info/WHEEL
setsig-1.0.0.dist-info/top_level.txt
setsig-1.0.0.dist-info/RECORD
