Metadata-Version: 2.4
Name: setsig
Version: 1.0.0
Summary: This project sets signatures.
Author-email: Johannes <johannes.programming@gmail.com>
License: The MIT License (MIT)
Project-URL: Download, https://pypi.org/project/setsig/#files
Project-URL: Index, https://pypi.org/project/setsig/
Project-URL: Source, https://github.com/johannes-programming/setsig/
Project-URL: Website, https://setsig.johannes-programming.online/
Classifier: Development Status :: 5 - Production/Stable
Classifier: License :: OSI Approved :: MIT License
Classifier: Natural Language :: English
Classifier: Operating System :: OS Independent
Classifier: Programming Language :: Python
Classifier: Programming Language :: Python :: 3
Classifier: Programming Language :: Python :: 3 :: Only
Classifier: Typing :: Typed
Requires-Python: >=3.11
License-File: LICENSE.txt
Requires-Dist: setdoc>=1.2.4
Dynamic: license-file
